<?xml version="1.0" encoding="UTF-8"?>
<!DOCTYPE mapper PUBLIC "-//mybatis.org//DTD Mapper 3.0//EN" "http://mybatis.org/dtd/mybatis-3-mapper.dtd">
<mapper namespace="club.uctennis.tournament.domain.mapper.OnetimeTokensMapper">
  <resultMap id="BaseResultMap" type="club.uctennis.tournament.domain.model.OnetimeTokens">
    <!--
      WARNING - @mbg.generated
      This element is automatically generated by MyBatis Generator, do not modify.
    -->
    <id column="id" jdbcType="INTEGER" property="id" />
    <result column="pre_entry_id" jdbcType="INTEGER" property="preEntryId" />
    <result column="token" jdbcType="VARCHAR" property="token" />
    <result column="limited_date" jdbcType="TIMESTAMP" property="limitedDate" />
    <result column="create_date" jdbcType="TIMESTAMP" property="createDate" />
    <result column="update_date" jdbcType="TIMESTAMP" property="updateDate" />
  </resultMap>
  <sql id="Base_Column_List">
    <!--
      WARNING - @mbg.generated
      This element is automatically generated by MyBatis Generator, do not modify.
    -->
    id, pre_entry_id, token, limited_date, create_date, update_date
  </sql>
  <insert id="insertSelective" parameterType="club.uctennis.tournament.domain.model.OnetimeTokens">
    <!--
      WARNING - @mbg.generated
      This element is automatically generated by MyBatis Generator, do not modify.
    -->
    insert into onetime_tokens
    <trim prefix="(" suffix=")" suffixOverrides=",">
      <if test="id != null">
        id,
      </if>
      <if test="preEntryId != null">
        pre_entry_id,
      </if>
      <if test="token != null">
        token,
      </if>
      <if test="limitedDate != null">
        limited_date,
      </if>
      <if test="createDate != null">
        create_date,
      </if>
      <if test="updateDate != null">
        update_date,
      </if>
    </trim>
    <trim prefix="values (" suffix=")" suffixOverrides=",">
      <if test="id != null">
        #{id,jdbcType=INTEGER},
      </if>
      <if test="preEntryId != null">
        #{preEntryId,jdbcType=INTEGER},
      </if>
      <if test="token != null">
        #{token,jdbcType=VARCHAR},
      </if>
      <if test="limitedDate != null">
        #{limitedDate,jdbcType=TIMESTAMP},
      </if>
      <if test="createDate != null">
        #{createDate,jdbcType=TIMESTAMP},
      </if>
      <if test="updateDate != null">
        #{updateDate,jdbcType=TIMESTAMP},
      </if>
    </trim>
  </insert>
  <update id="updateByPrimaryKeySelective" parameterType="club.uctennis.tournament.domain.model.OnetimeTokens">
    <!--
      WARNING - @mbg.generated
      This element is automatically generated by MyBatis Generator, do not modify.
    -->
    update onetime_tokens
    <set>
      <if test="preEntryId != null">
        pre_entry_id = #{preEntryId,jdbcType=INTEGER},
      </if>
      <if test="token != null">
        token = #{token,jdbcType=VARCHAR},
      </if>
      <if test="limitedDate != null">
        limited_date = #{limitedDate,jdbcType=TIMESTAMP},
      </if>
      <if test="createDate != null">
        create_date = #{createDate,jdbcType=TIMESTAMP},
      </if>
      <if test="updateDate != null">
        update_date = #{updateDate,jdbcType=TIMESTAMP},
      </if>
    </set>
    where id = #{id,jdbcType=INTEGER}
  </update>
</mapper>